sphinxcontrib_mermaid-0.9-py3.10-nspkg.pth
sphinxcontrib/autoclassdiag.py
sphinxcontrib/exceptions.py
sphinxcontrib/mermaid.py
sphinxcontrib_mermaid-0.9.dist-info/LICENSE.rst
sphinxcontrib_mermaid-0.9.dist-info/METADATA
sphinxcontrib_mermaid-0.9.dist-info/WHEEL
sphinxcontrib_mermaid-0.9.dist-info/namespace_packages.txt
sphinxcontrib_mermaid-0.9.dist-info/top_level.txt
sphinxcontrib_mermaid-0.9.dist-info/RECORD
