Metadata-Version: 2.1
Name: sphinxcontrib-mermaid
Version: 0.9
Summary: Mermaid diagrams in yours Sphinx powered docs
Home-page: https://github.com/mgaitan/sphinxcontrib-mermaid
Download-URL: https://pypi.python.org/pypi/sphinxcontrib-mermaid
Author: Martín Gaitán
Author-email: gaitan@gmail.com
License: BSD
Platform: any
Classifier: Development Status :: 4 - Beta
Classifier: Environment :: Console
Classifier: Environment :: Web Environment
Classifier: Intended Audience :: Developers
Classifier: License :: OSI Approved :: BSD License
Classifier: Operating System :: OS Independent
Classifier: Programming Language :: Python
Classifier: Programming Language :: Python :: 3
Classifier: Programming Language :: Python :: 3.7
Classifier: Programming Language :: Python :: 3.8
Classifier: Programming Language :: Python :: 3.9
Classifier: Programming Language :: Python :: 3.10
Classifier: Programming Language :: Python :: 3.11
Classifier: Programming Language :: Python :: Implementation :: CPython
Classifier: Programming Language :: Python :: Implementation :: PyPy
Classifier: Topic :: Documentation
Classifier: Topic :: Utilities
Requires-Python: >=3.7
License-File: LICENSE.rst
